infosecmachines/__init__.py
infosecmachines/classes.py
infosecmachines/s4vimachines.py
infosecmachines/exceptions/__init__.py
infosecmachines-0.0.1.dist-info/licenses/LICENSE
infosecmachines-0.0.1.dist-info/METADATA
infosecmachines-0.0.1.dist-info/WHEEL
infosecmachines-0.0.1.dist-info/top_level.txt
infosecmachines-0.0.1.dist-info/RECORD
