Metadata-Version: 2.4
Name: infosecmachines
Version: 0.0.1
Summary: Infosec machines API created in Python
Home-page: https://github.com/SelfDreamer/Infosecmachines
Author: Flick
Project-URL: Homepage, https://github.com/SelfDreamer/Infosecmachines
Requires-Python: >=3.8
License-File: LICENSE
Requires-Dist: typeguard
Requires-Dist: yt_dlp
Requires-Dist: aiohttp
Requires-Dist: screeninfo
Requires-Dist: requests
Dynamic: home-page
Dynamic: license-file
